[
  {
    "lieu": "Messine, en Sicile",
    "epoque": "546",
    "nom": "Placide",
    "titre": "moine"
  },
  {
    "lieu": "Messine, en Sicile",
    "epoque": "546",
    "nom": "Eutychius",
    "titre": "moine"
  },
  {
    "lieu": "Messine, en Sicile",
    "epoque": "546",
    "nom": "Victorinus",
    "titre": "moine"
  },
  {
    "lieu": "Messine, en Sicile",
    "epoque": "546",
    "nom": "Flavia",
    "titre": "vierge"
  },
  {
    "lieu": "Messine, en Sicile",
    "epoque": "546",
    "nom": "Donat",
    "titre": "aucun"
  },
  {
    "lieu": "Messine, en Sicile",
    "epoque": "546",
    "nom": "Firmat",
    "titre": "diacre"
  },
  {
    "lieu": "Messine, en Sicile",
    "epoque": "546",
    "nom": "Fauste",
    "titre": "moine"
  },
  {
    "lieu": "Smyrne",
    "epoque": "171",
    "nom": "Thraséas",
    "titre": "évêque"
  },
  {
    "lieu": "Trèves",
    "epoque": "Dioclétien",
    "nom": "Palmatius",
    "titre": "aucun"
  },
  {
    "lieu": "Trèves",
    "epoque": "Dioclétien",
    "nom": "ses compagnons",
    "titre": "aucun"
  },
  {
    "lieu": "",
    "epoque": "Dioclétien",
    "nom": "Charitine",
    "titre": "vierge"
  },
  {
    "lieu": "Auxerre",
    "epoque": "cinquième ou sixième siècle",
    "nom": "Firmat",
    "titre": "diacre"
  },
  {
    "lieu": "Auxerre",
    "epoque": "cinquième ou sixième siècle",
    "nom": "Flavie",
    "titre": "vierge"
  },
  {
    "lieu": "Ravenne",
    "epoque": "",
    "nom": "Marcellin",
    "titre": "évêque"
  },
  {
    "lieu": "Valence, en Gaule",
    "epoque": "520",
    "nom": "Apollinaire",
    "titre": "évêque"
  },
  {
    "lieu": "Zamora",
    "epoque": "",
    "nom": "Attilan",
    "titre": "évêque"
  },
  {
    "lieu": "León, en Espagne",
    "epoque": "1006",
    "nom": "Froilan",
    "titre": "évêque"
  },
  {
    "lieu": "Rome",
    "epoque": "",
    "nom": "Galla",
    "titre": "veuve"
  }
]