[
  {
    "lieu": "Rome",
    "epoque": "1373",
    "nom": "Bridget",
    "titre": "sainte Veuve"
  },
  {
    "lieu": "",
    "epoque": "",
    "nom": "Siméon",
    "titre": "saint vieillard"
  },
  {
    "lieu": "Césarée",
    "epoque": "Empereur Dèce",
    "nom": "Réparate",
    "titre": "sainte Vierge et martyre"
  },
  {
    "lieu": "Thessalonique",
    "epoque": "Empereur Maximien",
    "nom": "Démétrius",
    "titre": "saint Proconsul"
  },
  {
    "lieu": "Thessalonique",
    "epoque": "Empereur Maximien",
    "nom": "Nestor",
    "titre": "saint martyr"
  },
  {
    "lieu": "Séville",
    "epoque": "",
    "nom": "Pierre",
    "titre": "saint martyr"
  },
  {
    "lieu": "Laodicée",
    "epoque": "Empereur Dioclétien",
    "nom": "Artemon",
    "titre": "saint Prêtre"
  },
  {
    "lieu": "Lyon",
    "epoque": "",
    "nom": "Bénédicte",
    "titre": "sainte Vierge et martyre"
  },
  {
    "lieu": "Ancône",
    "epoque": "Empereur Dioclétien",
    "nom": "Palatias",
    "titre": "saint"
  },
  {
    "lieu": "Ancône",
    "epoque": "Empereur Dioclétien",
    "nom": "Laurentia",
    "titre": "sainte"
  },
  {
    "lieu": "Rouen",
    "epoque": "cinquième siècle",
    "nom": "Évode",
    "titre": "Évêque"
  },
  {
    "lieu": "Jérusalem",
    "epoque": "460",
    "nom": "Pélagie",
    "titre": "sainte"
  }
]