[
  {
    "lieu": "",
    "epoque": "",
    "nom": "Rufus",
    "titre": "aucun"
  },
  {
    "lieu": "Rome",
    "epoque": "",
    "nom": "Celse",
    "titre": "martyr"
  },
  {
    "lieu": "Rome",
    "epoque": "",
    "nom": "Clément",
    "titre": "martyr"
  },
  {
    "lieu": "Ostie",
    "epoque": "",
    "nom": "Démétrius",
    "titre": "martyr"
  },
  {
    "lieu": "Ostie",
    "epoque": "",
    "nom": "Honorius",
    "titre": "martyr"
  },
  {
    "lieu": "Reims",
    "epoque": "1192",
    "nom": "Albert",
    "titre": "évêque"
  },
  {
    "lieu": "Espagne",
    "epoque": "",
    "nom": "Honorius",
    "titre": "martyr"
  },
  {
    "lieu": "Espagne",
    "epoque": "",
    "nom": "Eutychius",
    "titre": "martyr"
  },
  {
    "lieu": "Espagne",
    "epoque": "",
    "nom": "Étienne",
    "titre": "martyr"
  },
  {
    "lieu": "Pamphylie",
    "epoque": "sous l'Empereur Aurélien",
    "nom": "Héliodore",
    "titre": "martyr"
  },
  {
    "lieu": "Rome",
    "epoque": "",
    "nom": "Gélase",
    "titre": "pape"
  },
  {
    "lieu": "Vérone",
    "epoque": "",
    "nom": "Maur",
    "titre": "évêque"
  },
  {
    "lieu": "monastère de Bobbio",
    "epoque": "",
    "nom": "Colomban",
    "titre": "abbé"
  }
]