[
  {
    "lieu": "Tarse, en Cilicie",
    "epoque": "sous l'Empereur Dioclétien",
    "nom": "Tharacus",
    "titre": "martyr"
  },
  {
    "lieu": "Tarse, en Cilicie",
    "epoque": "sous l'Empereur Dioclétien",
    "nom": "Probus",
    "titre": "martyr"
  },
  {
    "lieu": "Tarse, en Cilicie",
    "epoque": "sous l'Empereur Dioclétien",
    "nom": "Andronicus",
    "titre": "martyr"
  },
  {
    "lieu": "Vexin",
    "epoque": "",
    "nom": "Nicasius",
    "titre": "Évêque"
  },
  {
    "lieu": "Vexin",
    "epoque": "",
    "nom": "Quirinus",
    "titre": "Prêtre"
  },
  {
    "lieu": "Vexin",
    "epoque": "",
    "nom": "Scubiculus",
    "titre": "Diacre"
  },
  {
    "lieu": "Vexin",
    "epoque": "",
    "nom": "Pientia",
    "titre": "Vierge"
  },
  {
    "lieu": "",
    "epoque": "",
    "nom": "Anastase",
    "titre": "Prêtre"
  },
  {
    "lieu": "",
    "epoque": "",
    "nom": "Placide",
    "titre": "martyr"
  },
  {
    "lieu": "",
    "epoque": "",
    "nom": "Génésius",
    "titre": "martyr"
  },
  {
    "lieu": "Thébaïde",
    "epoque": "",
    "nom": "Sarmatas",
    "titre": "disciple"
  },
  {
    "lieu": "Besançon, en Gaule",
    "epoque": "",
    "nom": "Germanus",
    "titre": "Évêque"
  },
  {
    "lieu": "Uzès, en Gaule",
    "epoque": "sixième siècle",
    "nom": "Firmin",
    "titre": "Confesseur"
  },
  {
    "lieu": "Irlande",
    "epoque": "600",
    "nom": "Kenneth",
    "titre": "Abbé"
  },
  {
    "lieu": "Lierre, en Belgique",
    "epoque": "huitième siècle",
    "nom": "Gummar",
    "titre": "Confesseur"
  },
  {
    "lieu": "Rennes, en Gaule",
    "epoque": "neuvième siècle",
    "nom": "Émilien",
    "titre": "Confesseur"
  },
  {
    "lieu": "Tarse, en Cilicie",
    "epoque": "",
    "nom": "Zénais",
    "titre": "sœur"
  },
  {
    "lieu": "Tarse, en Cilicie",
    "epoque": "",
    "nom": "Philonille",
    "titre": "sœur"
  },
  {
    "lieu": "Vérone",
    "epoque": "cinquième siècle",
    "nom": "Placidie",
    "titre": "Vierge"
  }
]