[
  {
    "lieu": "Rome, sur la Voie Aurélienne",
    "epoque": "",
    "nom": "Callixte",
    "titre": "Pape"
  },
  {
    "lieu": "Césarée, en Palestine",
    "epoque": "",
    "nom": "Fortunée",
    "titre": "Vierge et martyre"
  },
  {
    "lieu": "",
    "epoque": "",
    "nom": "Carpone",
    "titre": "martyr"
  },
  {
    "lieu": "",
    "epoque": "",
    "nom": "Évariste",
    "titre": "martyr"
  },
  {
    "lieu": "",
    "epoque": "",
    "nom": "Priscien",
    "titre": "martyr"
  },
  {
    "lieu": "",
    "epoque": "",
    "nom": "Saturnin",
    "titre": "martyr"
  },
  {
    "lieu": "",
    "epoque": "",
    "nom": "Lupus",
    "titre": "martyr"
  },
  {
    "lieu": "Rimini",
    "epoque": "quatrième siècle",
    "nom": "Gaudence",
    "titre": "Évêque"
  },
  {
    "lieu": "Todi",
    "epoque": "",
    "nom": "Fortunat",
    "titre": "Évêque"
  },
  {
    "lieu": "Wurtzbourg",
    "epoque": "huitième siècle",
    "nom": "Burchard",
    "titre": "Évêque"
  },
  {
    "lieu": "Bruges, en Flandre",
    "epoque": "vers la fin du quatrième siècle",
    "nom": "Donatien",
    "titre": "Évêque"
  },
  {
    "lieu": "Trèves",
    "epoque": "sixième siècle",
    "nom": "Rustique",
    "titre": "Évêque"
  },
  {
    "lieu": "",
    "epoque": "1060",
    "nom": "Dominique",
    "titre": "aucun"
  },
  {
    "lieu": "Latium",
    "epoque": "",
    "nom": "Bernard",
    "titre": "Confesseur"
  }
]